cv2_collage/LICENSE
cv2_collage/README.MD
cv2_collage/__init__.py
cv2_collage/requirements.txt
cv2_collage/thirdparty.json
cv2_collage-0.10.dist-info/LICENSE.rst
cv2_collage-0.10.dist-info/METADATA
cv2_collage-0.10.dist-info/WHEEL
cv2_collage-0.10.dist-info/top_level.txt
cv2_collage-0.10.dist-info/RECORD
